setup.py
bindings/__init__.py
bindings/binding.py
bindings/document.py
bindings/multiref.py
bindings/rpc.py
mx/__init__.py
mx/appender.py
mx/basic.py
mx/core.py
mx/encoded.py
mx/literal.py
mx/typer.py
sax/__init__.py
sax/attribute.py
sax/date.py
sax/document.py
sax/element.py
sax/enc.py
sax/parser.py
sax/text.py
suds_ceeme.egg-info/PKG-INFO
suds_ceeme.egg-info/SOURCES.txt
suds_ceeme.egg-info/dependency_links.txt
suds_ceeme.egg-info/requires.txt
suds_ceeme.egg-info/top_level.txt
transport/__init__.py
transport/http.py
transport/https.py
transport/options.py
umx/__init__.py
umx/attrlist.py
umx/basic.py
umx/core.py
umx/encoded.py
umx/typed.py
xsd/__init__.py
xsd/deplist.py
xsd/doctor.py
xsd/query.py
xsd/schema.py
xsd/sxbase.py
xsd/sxbasic.py
xsd/sxbuiltin.py