Metadata-Version: 1.0
Name: suds-ceeme
Version: 0.4
Summary: Lightweight SOAP client - fork of suds
Home-page: https://hg.ceeme-services.com/Forks/suds
Author: CEEME
Author-email: noreply@ceeme-services.com
License: UNKNOWN
Platform: UNKNOWN
